pysosirius/__init__.py
pysosirius/defaults.py
pysosirius/pysosirius.py
pysosirius/setup.py
pysosirius/sirius_channel.py
pysosirius/sirius_playing.py
pysosirius/common/__init__.py
pysosirius/common/exceptions.py
pysosirius/database/PySoSirius.db
pysosirius/database/__init__.py
pysosirius/database/manager.py
pysosirius/web/__init__.py
pysosirius/web/utilities.py
pysosirius-0.0.9.dist-info/DESCRIPTION.rst
pysosirius-0.0.9.dist-info/METADATA
pysosirius-0.0.9.dist-info/RECORD
pysosirius-0.0.9.dist-info/WHEEL
pysosirius-0.0.9.dist-info/metadata.json
pysosirius-0.0.9.dist-info/top_level.txt
pysosirius-0.0.9.dist-info/zip-safe
