Metadata-Version: 2.0
Name: pysosirius
Version: 0.0.9
Summary: Unofficial Sirius XM API
Home-page: https://github.com/T-Santos/PySoSirius
Author: Tyler Santos
Author-email: 1tsantos7+pysosirius@Gmail.com
License: MIT
Keywords: Sirius SiriusXM XM Music
Platform: UNKNOWN
Classifier: Development Status :: 1 - Planning
Classifier: Intended Audience :: Developers
Classifier: License :: OSI Approved :: MIT License
Classifier: Programming Language :: Python :: 2.7
Requires-Dist: bs4
Requires-Dist: requests
Requires-Dist: selenium
